bmi_topography/__init__.py
bmi_topography/_version.py
bmi_topography/api_key.py
bmi_topography/bbox.py
bmi_topography/bmi.py
bmi_topography/cli.py
bmi_topography/errors.py
bmi_topography/topography.py
bmi_topography-0.9.0.dist-info/licenses/LICENSE.md
bmi_topography-0.9.0.dist-info/METADATA
bmi_topography-0.9.0.dist-info/WHEEL
bmi_topography-0.9.0.dist-info/entry_points.txt
bmi_topography-0.9.0.dist-info/top_level.txt
bmi_topography-0.9.0.dist-info/RECORD
