Metadata-Version: 2.4
Name: bmi-topography
Version: 0.9.0
Summary: Fetch and cache land elevation data from OpenTopography
Author-email: Mark Piper <mark.piper@colorado.edu>
Maintainer-email: Mark Piper <mark.piper@colorado.edu>, Eric Hutton <eric.hutton@colorado.edu>
License: MIT License
Project-URL: Homepage, https://csdms.colorado.edu
Project-URL: Documentation, https://bmi-topography.csdms.io/
Project-URL: Repository, https://github.com/csdms/bmi-topography
Project-URL: Changelog, https://github.com/csdms/bmi-topography/blob/main/CHANGES.md
Project-URL: Forum, https://forum.csdms.io
Keywords: bmi,srtm,alos,nasadem,copernicus,topography,elevation,dem,data,csdms,usgs,gedi,gebco,mrdem
Classifier: Programming Language :: Python :: 3
Classifier: Programming Language :: Python :: 3.10
Classifier: Programming Language :: Python :: 3.11
Classifier: Programming Language :: Python :: 3.12
Classifier: Programming Language :: Python :: 3.13
Classifier: License :: OSI Approved :: MIT License
Classifier: Operating System :: OS Independent
Classifier: Intended Audience :: Developers
Classifier: Intended Audience :: Science/Research
Classifier: Intended Audience :: Education
Requires-Python: >=3.10
License-File: LICENSE.md
Requires-Dist: requests
Requires-Dist: numpy
Requires-Dist: click
Requires-Dist: pyyaml
Requires-Dist: xarray
Requires-Dist: rioxarray
Requires-Dist: bmipy
Provides-Extra: dev
Requires-Dist: nox; extra == "dev"
Provides-Extra: build
Requires-Dist: build; extra == "build"
Requires-Dist: twine; extra == "build"
Requires-Dist: zest.releaser; extra == "build"
Provides-Extra: testing
Requires-Dist: pytest; extra == "testing"
Requires-Dist: pytest-cov; extra == "testing"
Requires-Dist: pytest-datadir; extra == "testing"
Requires-Dist: coverage; extra == "testing"
Requires-Dist: coveralls; extra == "testing"
Provides-Extra: docs
Requires-Dist: sphinx; extra == "docs"
Requires-Dist: myst_parser; extra == "docs"
Requires-Dist: importlib-metadata; extra == "docs"
Provides-Extra: examples
Requires-Dist: matplotlib; extra == "examples"
Dynamic: license-file
